creativecontrol_circuitpython_ltc166x.py
creativecontrol_circuitpython_ltc166x-1.2.3.dist-info/LICENSE
creativecontrol_circuitpython_ltc166x-1.2.3.dist-info/METADATA
creativecontrol_circuitpython_ltc166x-1.2.3.dist-info/WHEEL
creativecontrol_circuitpython_ltc166x-1.2.3.dist-info/top_level.txt
creativecontrol_circuitpython_ltc166x-1.2.3.dist-info/RECORD
