Metadata-Version: 2.1
Name: creativecontrol-circuitpython-ltc166x
Version: 1.2.3
Summary: CircuitPython library for control of LTC166X 8-bit and 10-bit DACs.
Author-email: creativecontrol <t@creativecontrol.cc>
License: MIT
Project-URL: Homepage, https://github.com/creativecontrol/creativecontrol_CircuitPython_LTC166X
Keywords: adafruit,blinka,circuitpython,micropython,creativecontrol_circuitpython_ltc166x,LTC1660,LTC1665,DAC
Classifier: Intended Audience :: Developers
Classifier: Topic :: Software Development :: Libraries
Classifier: Topic :: Software Development :: Embedded Systems
Classifier: Topic :: System :: Hardware
Classifier: License :: OSI Approved :: MIT License
Classifier: Programming Language :: Python :: 3
License-File: LICENSE
Requires-Dist: Adafruit-Blinka
Requires-Dist: adafruit-circuitpython-busdevice
Provides-Extra: optional
